<?xml version="1.0" standalone="yes"?>
<RECORDS>
	<RECORD>
		<id>1001</id>
		<skillAreaType>0</skillAreaType>
		<skillEffectType>0</skillEffectType>
		<skillAdditionType>0</skillAdditionType>
		<skillName>测试</skillName>
	</RECORD>
	<RECORD>
		<id>1002</id>
		<skillAreaType>0</skillAreaType>
		<skillEffectType>0</skillEffectType>
		<skillAdditionType>0</skillAdditionType>
		<skillName>回复</skillName>
	</RECORD>
	<RECORD>
		<id>1101</id>
		<skillAreaType>0</skillAreaType>
		<skillEffectType>0</skillEffectType>
		<skillAdditionType>0</skillAdditionType>
		<skillName>火球</skillName>
	</RECORD>
</RECORDS>

